<?xml version="1.0" encoding="UTF-8"?>
<?xml-stylesheet type="text/xsl" href="/xsl/SGr.xsl"?>
<DeviceFrame xmlns="http://www.smartgridready.com/ns/V0/"
  xmlns:xsi="http://www.w3.org/2001/XMLSchema-instance"
  xsi:schemaLocation="http://www.smartgridready.com/ns/V0/ ../../SchemaDatabase/SGr/Product/Product.xsd">
  <deviceName>OptiHeat</deviceName>
  <manufacturerName>CTA AG</manufacturerName>
  <specificationOwnerIdentification>0</specificationOwnerIdentification>
  <releaseNotes>
    <state>Draft</state>
  </releaseNotes>
  <deviceInformation>
    <legibleDescription>
      <textElement>
        CTA Wärmepumpen mit OptiHeat Inverta(r)TWW 4esr, Eco 9e und Eco17a und
        SmartGridready Anbindung ermöglichen umweltfreundliches Heizen.
      </textElement>
      <language>de</language>
    </legibleDescription>
    <deviceCategory>HeatPumpAppliance</deviceCategory>
    <isLocalControl>true</isLocalControl>
    <softwareRevision>2.1.0</softwareRevision>
    <hardwareRevision>1.1.0</hardwareRevision>
    <brandName>OptiHeat Inverta</brandName>
    <powerSource>mains3Phase</powerSource>
    <nominalPower>5 - 35 kW</nominalPower>
    <manufacturerLabel>
			CTA OH Inverta Wärmepumpen
		</manufacturerLabel>
    <generalRemarks>CTA/mz  IBT/cb</generalRemarks>
    <levelOfOperation>4</levelOfOperation>
    <programmerHints>
      <textElement>
          This Gateway offers manufacturer specific control modes for HeatCoolCtrl and DomHotWaterCtrl.  
          Manufacurer specific data points use the preamble cta.
          Some data points support persistent memory functionality  (RWP) and limit data write operations to a couple 10'000 write cycles.
      </textElement>
      <language>en</language>
      <uri>https://cta.ch/privatkunden/produkte/oh-i-eco-sw</uri>
    </programmerHints>
  </deviceInformation>
  <interfaceList>
    <modbusInterface>
      <modbusInterfaceDescription>
        <modbusInterfaceSelection>TCPIP</modbusInterfaceSelection>
        <modbusTcp>
          <port>502</port>
          <address>192.168.99.55</address>
          <slaveId>1</slaveId>
        </modbusTcp>
        <firstRegisterAddressIsOne>false</firstRegisterAddressIsOne>
        <bitOrder>ChangeWordOrder</bitOrder>
        <masterFunctionsSupportedList>
          <masterFunctionsSupported>Primitives</masterFunctionsSupported>
        </masterFunctionsSupportedList>
      </modbusInterfaceDescription>
      <functionalProfileList>
        <functionalProfileListElement>
          <functionalProfile>
            <functionalProfileName>DeviceInformation</functionalProfileName>
            <functionalProfileIdentification>
              <specificationOwnerIdentification>0</specificationOwnerIdentification>
              <functionalProfileCategory>DeviceInformation</functionalProfileCategory>
              <functionalProfileType>UNDEF</functionalProfileType>
              <levelOfOperation>4</levelOfOperation>
              <versionNumber>
                <primaryVersionNumber>0</primaryVersionNumber>
                <secondaryVersionNumber>2</secondaryVersionNumber>
                <subReleaseVersionNumber>1</subReleaseVersionNumber>
              </versionNumber>
            </functionalProfileIdentification>
            <legibleDescription>
              <textElement>Dieses Funktionsprofil ermöglicht das Handling von Datenpunkten, welche für das ganze Gerät gelten</textElement>
              <language>de</language>
            </legibleDescription>
          </functionalProfile>
          <dataPointList>
            <dataPointListElement>
              <dataPoint>
                <dataPointName>ctaRemoteCtrlTimeSec</dataPointName>
                <dataDirection>RW</dataDirection>
                <presenceLevel>M</presenceLevel>
                <dataType>
                  <int16U />
                </dataType>
                <unit>SECONDS</unit>
                <alternativeNames>
                  <sLV1Name>ctaRemoteCtrlTimeSec</sLV1Name>
                  <manufName>CTA_Ext_Communication_Handler</manufName>
                </alternativeNames>
                <legibleDescription>
                  <textElement>Countdown Variable in sec. Wenn 0, dann Ext. Kommunikation inaktiv., Max. Wert 3000</textElement>
                  <language>de</language>
                </legibleDescription>
                <programmerHints>
                  <textElement>remoteCtrlTimeSec is valid for external HeatCoolCtrl commands. It must be > 0 for keeping the external command / Setpoint valid.
                    CTA_Ext_Heating_Setpoints and / or  CTA_Ext_Cooling_Setpoints must be set t true that the appropriate setpoint can be set. 
                     Check the datapoints ctaRemoteHCTempSetptEnable within the HeatCoolCtrl functional profiles for further information.
                     </textElement>
                  <language>en</language>
                </programmerHints>
              </dataPoint>
              <genericAttributes>
                <maxVal>3000</maxVal>
              </genericAttributes>
              <modbusDataPointConfiguration>
                <modbusDataType>
                  <int16U/>
                </modbusDataType>
                <address>990</address>
                <registerType>HoldRegister</registerType>
                <numberOfRegisters>1</numberOfRegisters>
              </modbusDataPointConfiguration>
            </dataPointListElement>                   
          </dataPointList>
        </functionalProfileListElement>
        <functionalProfileListElement>
          <functionalProfile>
            <functionalProfileName>HeatPumpBase</functionalProfileName>
            <functionalProfileIdentification>
              <specificationOwnerIdentification>0</specificationOwnerIdentification>
              <functionalProfileCategory>HeatPumpControl</functionalProfileCategory>
              <functionalProfileType>HeatPumpBase</functionalProfileType>
              <levelOfOperation>m</levelOfOperation>
              <versionNumber>
                <primaryVersionNumber>0</primaryVersionNumber>
                <secondaryVersionNumber>1</secondaryVersionNumber>
                <subReleaseVersionNumber>2</subReleaseVersionNumber>
              </versionNumber>
            </functionalProfileIdentification>
            <legibleDescription>
              <textElement>
                Das Profil definiert den Grundbaustein zur dynamischen Ansteuerung
                von Wärmepumpen über eine variable Beeinflussung der Sollwerte nach SGr Level 4.
                Der Betrieb der Wärmepumpe muss in sich sicher sein, unabhängig von den äusseren
                Vorgaben. Dieses Grundprofil definiert die Datenpunkte, welche zur Steuerung des
                Gerätes «Wärmepumpe» auf Level 4 grundsätzlich zur Verfügung gestellt werden und
                stellen die Version einer typischen EInfamilienhauswärmepumpe miz
                Aussentemperaturfühler dar. Für die einzelnen Heizkreise, Warmwasser,
                Pufferspeicher und das Energie-Monitoring sowie eine Verdichterdrehzahl /
                Leistungsregelung werden separate Profile zur Verfügung gestellt.
              </textElement>
              <language>de</language>
            </legibleDescription>
          </functionalProfile>
          <dataPointList>
            <dataPointListElement>
              <dataPoint>
                <dataPointName>ctaHPOpModeCmdFb</dataPointName>
                <dataDirection>R</dataDirection>
                <presenceLevel>O</presenceLevel>
                <dataType>
                  <enum>
                    <enumEntry>
                      <literal>HP_STANDBY</literal>
                      <ordinal>1</ordinal>
                      <description>WP in Stand by Modus</description>
                    </enumEntry>
                    <enumEntry>
                      <literal>HP_HEATING_OP</literal>
                      <ordinal>2</ordinal>
                      <description>Heizbetrieb aktiv</description>
                    </enumEntry>
                    <enumEntry>
                      <literal>HP_EMERG_HEATING_ACTIVE</literal>
                      <ordinal>3</ordinal>
                      <description>Notbetrieb Heizen aktiv</description>
                    </enumEntry>
                    <enumEntry>
                      <literal>HP_DOMHW_ACTIVE</literal>
                      <ordinal>4</ordinal>
                      <description>TWW Ladung aktiv</description>
                    </enumEntry>
                    <enumEntry>
                      <literal>HP_OMHW_EMERG_ACTIVE</literal>
                      <ordinal>5</ordinal>
                      <description>Notbetrieb TWW aktiv</description>
                    </enumEntry>
                    <enumEntry>
                      <literal>HP_ACTIVE_COOLING_OP</literal>
                      <ordinal>6</ordinal>
                      <description>Aktivkühlbetrieb aktiv</description>
                    </enumEntry>
                    <enumEntry>
                      <literal>HP_MANUAL_OP</literal>
                      <ordinal>7</ordinal>
                      <description>Manueller Betrieb</description>
                    </enumEntry>
                    <enumEntry>
                      <literal>HP_BUFFER_LOAD_ACTIVE</literal>
                      <ordinal>8</ordinal>
                      <description>Heizungsspeicher Ladebetrieb ein</description>
                    </enumEntry>
                    <enumEntry>
                      <literal>HP_EXTERNAL_CTRL</literal>
                      <ordinal>9</ordinal>
                      <description>Externer Betrieb ein</description>
                    </enumEntry>
                    <enumEntry>
                      <literal>HP_DIRECT_DISTRIBUTION</literal>
                      <ordinal>10</ordinal>
                      <description>Verteilkreis-ohne Puffer Betrieb</description>
                    </enumEntry>
                    <enumEntry>
                      <literal>HP_DEFROST_ACTIVE</literal>
                      <ordinal>11</ordinal>
                      <description>Abtauvorgang aktiv</description>
                    </enumEntry>
                    <enumEntry>
                      <literal>HP_PASSIVE_COOLING_OP</literal>
                      <ordinal>12</ordinal>
                      <description>Kältegeführter Betrieb (Prozesskühlen)</description>
                    </enumEntry>
                    <enumEntry>
                      <literal>HP_RESERVE</literal>
                      <ordinal>13</ordinal>
                      <description>Reserve</description>
                    </enumEntry>
                    <enumEntry>
                      <literal>HP_COMBINDED_BUFFER_LOADING</literal>
                      <ordinal>14</ordinal>
                      <description>TWW Legio mit El. Einsatz K6 und parallel Heizungsbetrieb (Pufferladung)</description>
                    </enumEntry>
                  </enum>
                </dataType>
                <unit>NONE</unit>
                <alternativeNames>
                  <sLV1Name>ctaHPOpModeCmdFb</sLV1Name>
                  <manufName>CTA_HeatPump_FSM</manufName>
                </alternativeNames>
                <legibleDescription>
                  <textElement>Status Code Betriebsart gem. Liste, eher als OpState führen?</textElement>
                  <language>de</language>
                </legibleDescription>
              </dataPoint>
              <modbusDataPointConfiguration>
                <modbusDataType>
                  <int16U />
                </modbusDataType>
                <address>2204</address>
                <registerType>InputRegister</registerType>
                <numberOfRegisters>1</numberOfRegisters>
              </modbusDataPointConfiguration>
            </dataPointListElement>
            <dataPointListElement>
              <dataPoint>
                <dataPointName>ctaHPOpState</dataPointName>
                <dataDirection>R</dataDirection>
                <presenceLevel>M</presenceLevel>
                <dataType>
                  <enum>
                    <enumEntry>
                      <literal>HP_STANDBY</literal>
                      <ordinal>1</ordinal>
                      <description>Stand by</description>
                    </enumEntry>
                    <enumEntry>
                      <literal>HP_ALARM_OFF</literal>
                      <ordinal>2</ordinal>
                      <description>Alarm aus</description>
                    </enumEntry>            
                    <enumEntry>
                      <literal>HP_MANUAL_OP</literal>
                      <ordinal>7</ordinal>
                      <description>Manueller Betrieb</description>
                    </enumEntry>
                    <enumEntry>
                      <literal>HP_STARTING</literal>
                      <ordinal>8</ordinal>
                      <description>Startphase</description>
                    </enumEntry>      
                    <enumEntry>
                      <literal>HP_PRESSURE_DIFF</literal>
                      <ordinal>14</ordinal>
                      <description>Gesperrt aufgrund Druckdifferenz beim Start</description>
                    </enumEntry>
                    <enumEntry>
                      <literal>HP_HEATING</literal>
                      <ordinal>16</ordinal>
                      <description>Heizbetrieb aktiv</description>
                    </enumEntry>
                    <enumEntry>
                      <literal>HP_COMP_START_ERR</literal>
                      <ordinal>17</ordinal>
                      <description>Start nach VD Startfehler</description>
                    </enumEntry>
                    <enumEntry>
                      <literal>HP_OFF_OUT_OFF_LIMITS</literal>
                      <ordinal>18</ordinal>
                      <description>Oel Rückführung aktiv></description>
                    </enumEntry>
                  </enum>
                </dataType>
                <unit>NONE</unit>
                <alternativeNames>
                  <sLV1Name>ctaHPOpState</sLV1Name>
                  <manufName>CTA_UnitStatus</manufName>
                </alternativeNames>
                <legibleDescription>
                  <textElement>Status Code Kältekreis gem. Liste</textElement>
                  <language>de</language>
                </legibleDescription>
              </dataPoint>
              <modbusDataPointConfiguration>
                <modbusDataType>
                  <int16U />
                </modbusDataType>
                <address>2202</address>
                <registerType>InputRegister</registerType>
                <numberOfRegisters>1</numberOfRegisters>
              </modbusDataPointConfiguration>
            </dataPointListElement>
            <dataPointListElement>
              <dataPoint>
                <dataPointName>ErrorNrSGr</dataPointName>
                <dataDirection>R</dataDirection>
                <presenceLevel>M</presenceLevel>
                <dataType>
                  <int16 />
                </dataType>
                <unit>NONE</unit>
                <alternativeNames>
                  <sLV1Name>ErrorNrSGr</sLV1Name>
                  <manufName>GlbAl</manufName>
                </alternativeNames>
                <legibleDescription>
                  <textElement>Statusanzeige Aktiver Alarm 1=Aktiv (zeitverzögert 90s od. gemäss
                    Einstellung)</textElement>
                  <language>de</language>
                </legibleDescription>
              </dataPoint>
              <modbusDataPointConfiguration>
                <modbusDataType>
                  <int16 />
                </modbusDataType>
                <address>2210</address>
                <registerType>InputRegister</registerType>
                <numberOfRegisters>1</numberOfRegisters>
              </modbusDataPointConfiguration>
              <modbusAttributes>
                <scalingFactor>
                  <multiplicator>1</multiplicator>
                  <powerof10>0</powerof10>
                </scalingFactor>
              </modbusAttributes>
            </dataPointListElement>
            <dataPointListElement>
              <dataPoint>
                <dataPointName>OutsideAirTemp</dataPointName>
                <dataDirection>R</dataDirection>
                <presenceLevel>M</presenceLevel>
                <dataType>
                  <float32 />
                </dataType>
                <unit>DEGREES_CELSIUS</unit>
                <alternativeNames>
                  <sLV1Name>OutsideAirTemp</sLV1Name>
                  <manufName>CTA_Outdoor_Temp</manufName>
                </alternativeNames>
                <legibleDescription>
                  <textElement>
                    Aktuelle Aussentemperatur (gemessen über Aussenfühler)
                  </textElement>
                  <language>de</language>
                </legibleDescription>
              </dataPoint>
              <modbusDataPointConfiguration>
                <modbusDataType>
                  <float32 />
                </modbusDataType>
                <address>2000</address>
                <registerType>InputRegister</registerType>
                <numberOfRegisters>2</numberOfRegisters>
              </modbusDataPointConfiguration>
            </dataPointListElement>
            <dataPointListElement>
              <dataPoint>
                <dataPointName>SupplyWaterTemp</dataPointName>
                <dataDirection>R</dataDirection>
                <presenceLevel>M</presenceLevel>
                <dataType>
                  <float32 />
                </dataType>
                <unit>DEGREES_CELSIUS</unit>
                <alternativeNames>
                  <sLV1Name>SupplyWaterTemp</sLV1Name>
                  <manufName>CTA_B21_Temp</manufName>
                </alternativeNames>
                <legibleDescription>
                  <textElement>Hz Vorlauftemperatur in °C</textElement>
                  <language>de</language>
                </legibleDescription>
              </dataPoint>
              <modbusDataPointConfiguration>
                <modbusDataType>
                  <float32 />
                </modbusDataType>
                <address>2002</address>
                <registerType>InputRegister</registerType>
                <numberOfRegisters>2</numberOfRegisters>
              </modbusDataPointConfiguration>
            </dataPointListElement>
            <dataPointListElement>
              <dataPoint>
                <dataPointName>ReturnSupplyWaterTemp</dataPointName>
                <dataDirection>R</dataDirection>
                <presenceLevel>O</presenceLevel>
                <dataType>
                  <float32 />
                </dataType>
                <unit>DEGREES_CELSIUS</unit>
                <alternativeNames>
                  <sLV1Name>ReturnSupplyWaterTemp</sLV1Name>
                  <manufName>CTA_B71_Temp</manufName>
                </alternativeNames>
                <legibleDescription>
                  <textElement>Auslesen der aktuellen aktuellen-Temperatur des Rücklaufs. Hz
                    Rücklauftemperatur in °C</textElement>
                  <language>de</language>
                </legibleDescription>
              </dataPoint>
              <modbusDataPointConfiguration>
                <modbusDataType>
                  <float32 />
                </modbusDataType>
                <address>2004</address>
                <registerType>InputRegister</registerType>
                <numberOfRegisters>2</numberOfRegisters>
              </modbusDataPointConfiguration>
            </dataPointListElement>
            <dataPointListElement>
              <dataPoint>
                <dataPointName>SourceTemp</dataPointName>
                <dataDirection>R</dataDirection>
                <presenceLevel>O</presenceLevel>
                <dataType>
                  <float32 />
                </dataType>
                <unit>DEGREES_CELSIUS</unit>
                <alternativeNames>
                  <sLV1Name>SourceTemp</sLV1Name>
                  <manufName>CTA_B91_Temp</manufName>
                </alternativeNames>
                <legibleDescription>
                  <textElement>Auslesen der aktuellen Temperaturen der WP-Quelle (SoleWasser oder
                    Luft)</textElement>
                  <language>de</language>
                </legibleDescription>
              </dataPoint>
              <modbusDataPointConfiguration>
                <modbusDataType>
                  <float32 />
                </modbusDataType>
                <address>2006</address>
                <registerType>InputRegister</registerType>
                <numberOfRegisters>2</numberOfRegisters>
              </modbusDataPointConfiguration>
            </dataPointListElement>
          </dataPointList>
        </functionalProfileListElement>
        <functionalProfileListElement>
          <functionalProfile>
            <functionalProfileName>PowerCtrl</functionalProfileName>
            <functionalProfileIdentification>
              <specificationOwnerIdentification>0</specificationOwnerIdentification>
              <functionalProfileCategory>HeatPumpControl</functionalProfileCategory>
              <functionalProfileType>PowerCtrl</functionalProfileType>
              <levelOfOperation>4m</levelOfOperation>
              <versionNumber>
                <primaryVersionNumber>0</primaryVersionNumber>
                <secondaryVersionNumber>1</secondaryVersionNumber>
                <subReleaseVersionNumber>2</subReleaseVersionNumber>
              </versionNumber>
            </functionalProfileIdentification>
            <legibleDescription>
              <textElement>Die Leistungssteuerung steuert die Verdichterdrehzahl. Dieser Sollwert wird nur bei Trink-Warmwasserbedarf berücksichtigt.
              Der Bedarf kann durch die Erhöhung des DomHotWTempStpt-Wertes erzeugt werden.</textElement>              
              <language>de</language>
            </legibleDescription>
          </functionalProfile>
          <dataPointList>
            <dataPointListElement>
              <dataPoint>
                <dataPointName>PowerCtrlStpt</dataPointName>
                <dataDirection>RWP</dataDirection>
                <presenceLevel>M</presenceLevel>
                <dataType>
                  <float32 />
                </dataType>
                <unit>PERCENT</unit>
                <alternativeNames>
                  <manufName>CTA_DWRequest</manufName>
                </alternativeNames>
                <legibleDescription>
                  <textElement>VD-Drehzahl in % bei TWW Ladung (Empfehlung 38)</textElement>
                  <language>de</language>
                </legibleDescription>
              </dataPoint>
              <genericAttributes>
                <maxVal>100.0</maxVal>
                <minVal>38.0</minVal>
                <!-- TODO check whether this is needed
                <unitConversionMultiplicator>2.0</unitConversionMultiplicator>
                -->
              </genericAttributes>
              <modbusDataPointConfiguration>
                <modbusDataType>
                  <float32 />
                </modbusDataType>
                <address>1028</address>
                <registerType>HoldRegister</registerType>
                <numberOfRegisters>2</numberOfRegisters>
              </modbusDataPointConfiguration>
            </dataPointListElement>
            <dataPointListElement>
              <dataPoint>
                <dataPointName>ActSpeed</dataPointName>
                <dataDirection>R</dataDirection>
                <presenceLevel>M</presenceLevel>
                <dataType>
                  <float32 />
                </dataType>
                <unit>REVOLUTIONS_PER_MINUTE</unit>
                <alternativeNames>
                	<sLV1Name>ActSpeed</sLV1Name>
                	<manufName>State_CompRPS</manufName></alternativeNames>
                <legibleDescription>
                  <textElement>
                    Effektive Drehzahl des Verdichters
                  </textElement>
                  <language>de</language>
                </legibleDescription>
              </dataPoint>
              <genericAttributes>
                <unitConversionMultiplicator>60.0</unitConversionMultiplicator>
              </genericAttributes>
              <modbusDataPointConfiguration>
                <modbusDataType>
                  <float32 />
                </modbusDataType>
                <address>2030</address>
                <registerType>InputRegister</registerType>
                <numberOfRegisters>2</numberOfRegisters>
              </modbusDataPointConfiguration>
            </dataPointListElement>
            <dataPointListElement>
              <dataPoint>
                <dataPointName>ActPowerACtot</dataPointName>
                <dataDirection>R</dataDirection>
                <presenceLevel>O</presenceLevel>
                <dataType>
                  <float32 />
                </dataType>
                <unit>KILOWATT_HOURS</unit>
                <alternativeNames>
                	<sLV1Name>ActPowerACtot</sLV1Name>
                	<manufName>State_CompPower</manufName></alternativeNames>
                <legibleDescription>
                  <textElement>
                    Effektive elektrischen Aufnahmeleistung des Verdichters
                  </textElement>
                  <language>de</language>
                </legibleDescription>
              </dataPoint>
              <modbusDataPointConfiguration>
                <modbusDataType>
                  <float32 />
                </modbusDataType>
                <address>2032</address>
                <registerType>InputRegister</registerType>
                <numberOfRegisters>2</numberOfRegisters>
              </modbusDataPointConfiguration>
            </dataPointListElement>
          </dataPointList>
        </functionalProfileListElement>
        <functionalProfileListElement>
          <functionalProfile>
            <functionalProfileName>HeatCoolCtrl_1</functionalProfileName>
            <functionalProfileIdentification>
              <specificationOwnerIdentification>0</specificationOwnerIdentification>
              <functionalProfileCategory>HeatPumpControl</functionalProfileCategory>
              <functionalProfileType>HeatCoolCtrl</functionalProfileType>
              <levelOfOperation>4m</levelOfOperation>
              <versionNumber>
                <primaryVersionNumber>0</primaryVersionNumber>
                <secondaryVersionNumber>1</secondaryVersionNumber>
                <subReleaseVersionNumber>2</subReleaseVersionNumber>
              </versionNumber>
            </functionalProfileIdentification>
            <legibleDescription>
              <textElement>
                Dieses Profil definiert die erweiterten Datenpunkte zum Grundprofil "HeatPumpBase",
                welche zur Steuerung eines Heiz- oder Kühlkreises zur Verfügung gestellt werden.
                Derselbe physikalische Kreislauf kann entweder für das Heizen oder das Kühlen
                verwendet werden. Das Heiz-/Kühlkreisprofil muss immer in Kombination mit dem
                Grundprofil der Wärmepumpe bewirtschaftet werden. Es können mehrere
                Heiz-/Kühlkreisprofile definiert werden.
              </textElement>
              <language>de</language>
            </legibleDescription>
          </functionalProfile>
          <dataPointList>
            <dataPointListElement>
              <dataPoint>
                <dataPointName>ctaHCOpModeCmd</dataPointName>
                <dataDirection>RWP</dataDirection>
                <presenceLevel>M</presenceLevel>
                <dataType>
                  <enum>
                    <enumEntry>
                      <literal>HC_EXT_CTRL</literal>
                      <ordinal>0</ordinal>
                      <description>Extern gesteuert</description>
                    </enumEntry>
                    <enumEntry>
                      <literal>HC_AUTO</literal>
                      <ordinal>1</ordinal>
                      <description>Standby Betrieb</description>
                    </enumEntry>
                    <enumEntry>
                      <literal>HC_HEAT_COMF</literal>
                      <ordinal>2</ordinal>
                      <description>Komfort Betrieb</description>
                    </enumEntry>
                    <enumEntry>
                      <literal>HC_HEAT_ECO</literal>
                      <ordinal>3</ordinal>
                      <description>Reduzierter Betrieb</description>
                    </enumEntry>
                    <enumEntry>
                      <literal>HC_ANTIFREEZE</literal>
                      <ordinal>4</ordinal>
                      <description>Frostschutz / Aus</description>
                    </enumEntry>
                    <enumEntry>
                      <literal>HC_EMERGENCY_OP</literal>
                      <ordinal>5</ordinal>
                      <description>Notbetrieb</description>
                    </enumEntry>
                  </enum>
                </dataType>
                <unit>NONE</unit>
                <alternativeNames>
                  <sLV1Name>ctaHCOpModeCmd</sLV1Name>
                  <manufName>CTA_HK1_Status_UsrSet</manufName>
                </alternativeNames>
                <legibleDescription>
                  <textElement>Auslesen des aktuellen Status des Heizkreises</textElement>
                  <language>de</language>
                </legibleDescription>
              </dataPoint>
              <modbusDataPointConfiguration>
                <modbusDataType>
                  <int32U />
                </modbusDataType>
                <address>1003</address>
                <registerType>HoldRegister</registerType>
                <numberOfRegisters>2</numberOfRegisters>
              </modbusDataPointConfiguration>
            </dataPointListElement>
            <dataPointListElement>
              <dataPoint>
                <dataPointName>ctaHCOpState</dataPointName>
                <dataDirection>R</dataDirection>
                <presenceLevel>M</presenceLevel>
                <dataType>
                  <enum>
                    <enumEntry>
                      <literal>HC_EXT_CTRL</literal>
                      <ordinal>0</ordinal>
                      <description>Extern gesteuert</description>
                    </enumEntry>
                    <enumEntry>
                      <literal>HC_AUTO</literal>
                      <ordinal>1</ordinal>
                      <description>Standby Betrieb</description>
                    </enumEntry>
                    <enumEntry>
                      <literal>HC_HEAT_COMF</literal>
                      <ordinal>2</ordinal>
                      <description>Komfort Betrieb</description>
                    </enumEntry>
                    <enumEntry>
                      <literal>HC_HEAT_ECO</literal>
                      <ordinal>3</ordinal>
                      <description>Reduzierter Betrieb</description>
                    </enumEntry>
                    <enumEntry>
                      <literal>HC_ANTIFREEZE</literal>
                      <ordinal>4</ordinal>
                      <description>Frostschutz / Aus</description>
                    </enumEntry>
                    <enumEntry>
                      <literal>HC_EMERGENCY_OP</literal>
                      <ordinal>5</ordinal>
                      <description>Notbetrieb</description>
                    </enumEntry>
                  </enum>
                </dataType>
                <unit>NONE</unit>
                <alternativeNames>
                  <sLV1Name>ctaHCOpState</sLV1Name>
                  <manufName>CTA_HK1_Status_UsrSet</manufName>
                </alternativeNames>
                <legibleDescription>
                  <textElement>Auslesen des aktuellen Status des Heizkreises</textElement>
                  <language>de</language>
                </legibleDescription>
              </dataPoint>
              <modbusDataPointConfiguration>
                <modbusDataType>
                  <int32U />
                </modbusDataType>
                <address>1003</address>
                <registerType>HoldRegister</registerType>
                <numberOfRegisters>2</numberOfRegisters>
              </modbusDataPointConfiguration>
            </dataPointListElement>
            <dataPointListElement>
              <dataPoint>
                <dataPointName>SupplyWaterTemp</dataPointName>
                <dataDirection>R</dataDirection>
                <presenceLevel>O</presenceLevel>
                <dataType>
                  <float32 />
                </dataType>
                <unit>DEGREES_CELSIUS</unit>
                <alternativeNames>
                  <sLV1Name>SupplyWaterTemp</sLV1Name>
                  <manufName>CTA_B21_Temp</manufName>
                </alternativeNames>
                <legibleDescription>
                  <textElement>Auslesen der aktuellen aktuellen-Temperatur des Vorlaufs.</textElement>
                  <language>de</language>
                </legibleDescription>
              </dataPoint>
              <modbusDataPointConfiguration>
                <modbusDataType>
                  <float32 />
                </modbusDataType>
                <address>2002</address>
                <registerType>InputRegister</registerType>
                <numberOfRegisters>2</numberOfRegisters>
              </modbusDataPointConfiguration>
            </dataPointListElement>
            <dataPointListElement>
              <dataPoint>
                <dataPointName>SupplyWaterTempStpt</dataPointName>
                <dataDirection>RW</dataDirection>
                <presenceLevel>O</presenceLevel>
                <dataType>
                  <float32 />
                </dataType>
                <unit>DEGREES_CELSIUS</unit>
                <alternativeNames>
                  <sLV1Name>SupplyWaterTempStpt</sLV1Name>
                  <manufName>CTA_Ext_Heating_Setpoint</manufName>
                </alternativeNames>
                <legibleDescription>
                  <textElement>Setzen der aktuellen Soll-Temperatur des Vorlaufs (Grundwert).</textElement>
                  <language>de</language>
                </legibleDescription>
              </dataPoint>
              <modbusDataPointConfiguration>
                <modbusDataType>
                  <float32 />
                </modbusDataType>
                <address>1001</address>
                <registerType>HoldRegister</registerType>
                <numberOfRegisters>2</numberOfRegisters>
              </modbusDataPointConfiguration>
            </dataPointListElement>
            <dataPointListElement>
              <dataPoint>
                <dataPointName>ctaRemoteHCTempSetptEnable</dataPointName>
                <dataDirection>RW</dataDirection>
                <presenceLevel>M</presenceLevel>
                <dataType>
                  <boolean/>
                </dataType>
                <unit>NONE</unit>
                <alternativeNames>
                	<sLV1Name>ctaRemoteHCTempSetptEnable</sLV1Name>
                	<manufName>CTA_Ext_Heating_Command</manufName></alternativeNames>
                <legibleDescription>
                  <textElement>true um den Datenpunkt HeatCoolCtrl.SupplyWaterTempStpt zu aktvieren</textElement>
                  <language>de</language>
                </legibleDescription>
                <programmerHints>
                  <textElement>true sets the CTA_Ext_Heating_Setpoint to active AND forces the ctaHCOpModeCmd into HC_COMFORT mode as long ctaRemoteCtrlTimeSec > 0
                  when the ctaRemoteHCTempSetptEnable becomes 0, HeatCoolCtrl will stay in comfort mode until a new ctaHCOpModeCmd is set</textElement>
                  <language>en</language>
                </programmerHints>
              </dataPoint>
              <modbusDataPointConfiguration>
                <modbusDataType>
                  <int16 />
                </modbusDataType>
                <address>1000</address>
                <registerType>HoldRegister</registerType>
                <numberOfRegisters>1</numberOfRegisters>
              </modbusDataPointConfiguration>
            </dataPointListElement>
            <dataPointListElement>
              <dataPoint>
                <dataPointName>ReturnSupplyWaterTemp</dataPointName>
                <dataDirection>R</dataDirection>
                <presenceLevel>O</presenceLevel>
                <dataType>
                  <float32 />
                </dataType>
                <unit>DEGREES_CELSIUS</unit>
                <alternativeNames>
                  <sLV1Name>ReturnSupplyWaterTemp</sLV1Name>
                  <manufName>CTA_B71_Temp</manufName>
                </alternativeNames>
                <legibleDescription>
                  <textElement>Auslesen der aktuellen aktuellen-Temperatur des Rücklaufs.</textElement>
                  <language>de</language>
                </legibleDescription>
              </dataPoint>
              <modbusDataPointConfiguration>
                <modbusDataType>
                  <float32 />
                </modbusDataType>
                <address>2004</address>
                <registerType>InputRegister</registerType>
                <numberOfRegisters>2</numberOfRegisters>
              </modbusDataPointConfiguration>
            </dataPointListElement>
          </dataPointList>
        </functionalProfileListElement>
        
        
        <functionalProfileListElement>
          <functionalProfile>
            <functionalProfileName>HeatCoolCtrl_2</functionalProfileName>
            <functionalProfileIdentification>
              <specificationOwnerIdentification>0</specificationOwnerIdentification>
              <functionalProfileCategory>HeatPumpControl</functionalProfileCategory>
              <functionalProfileType>HeatCoolCtrl</functionalProfileType>
              <levelOfOperation>4m</levelOfOperation>
              <versionNumber>
                <primaryVersionNumber>0</primaryVersionNumber>
                <secondaryVersionNumber>1</secondaryVersionNumber>
                <subReleaseVersionNumber>2</subReleaseVersionNumber>
              </versionNumber>
            </functionalProfileIdentification>
            <legibleDescription>
              <textElement>
                Dieses Profil definiert die erweiterten Datenpunkte zum Grundprofil "HeatPumpBase",
                welche zur Steuerung eines Heiz- oder Kühlkreises zur Verfügung gestellt werden.
                Derselbe physikalische Kreislauf kann entweder für das Heizen oder das Kühlen
                verwendet werden. Das Heiz-/Kühlkreisprofil muss immer in Kombination mit dem
                Grundprofil der Wärmepumpe bewirtschaftet werden. Es können mehrere
                Heiz-/Kühlkreisprofile definiert werden.
              </textElement>
              <language>de</language>
            </legibleDescription>
          </functionalProfile>
          <dataPointList>
            <dataPointListElement>
              <dataPoint>
                <dataPointName>ctaHCOpModeCmd</dataPointName>
                <dataDirection>RWP</dataDirection>
                <presenceLevel>M</presenceLevel>
                <dataType>
                  <enum>
                    <enumEntry>
                      <literal>HC_EXT_CTRL</literal>
                      <ordinal>0</ordinal>
                      <description>Extern gesteuert</description>
                    </enumEntry>
                    <enumEntry>
                      <literal>HC_AUTO</literal>
                      <ordinal>1</ordinal>
                      <description>Standby Betrieb</description>
                    </enumEntry>
                    <enumEntry>
                      <literal>HC_HEAT_COMF</literal>
                      <ordinal>2</ordinal>
                      <description>Komfort Betrieb</description>
                    </enumEntry>
                    <enumEntry>
                      <literal>HC_HEAT_ECO</literal>
                      <ordinal>3</ordinal>
                      <description>Reduzierter Betrieb</description>
                    </enumEntry>
                    <enumEntry>
                      <literal>HC_ANTIFREEZE</literal>
                      <ordinal>4</ordinal>
                      <description>Frostschutz / Aus</description>
                    </enumEntry>
                    <enumEntry>
                      <literal>HC_EMERGENCY_OP</literal>
                      <ordinal>5</ordinal>
                      <description>Notbetrieb</description>
                    </enumEntry>
                  </enum>
                </dataType>
                <unit>NONE</unit>
                <alternativeNames>
                  <sLV1Name>ctaHCOpModeCmd</sLV1Name>
                  <manufName>CTA_HK2_Status_UsrSet</manufName>
                </alternativeNames>
                <legibleDescription>
                  <textElement>Auslesen des aktuellen Status des Heizkreises</textElement>
                  <language>de</language>
                </legibleDescription>
              </dataPoint>
              <modbusDataPointConfiguration>
                <modbusDataType>
                  <int32U />
                </modbusDataType>
                <address>1103</address>
                <registerType>HoldRegister</registerType>
                <numberOfRegisters>2</numberOfRegisters>
              </modbusDataPointConfiguration>
            </dataPointListElement>
            <dataPointListElement>
              <dataPoint>
                <dataPointName>ctaHCOpState</dataPointName>
                <dataDirection>R</dataDirection>
                <presenceLevel>M</presenceLevel>
                <dataType>
                  <enum>
                    <enumEntry>
                      <literal>HC_EXT_CTRL</literal>
                      <ordinal>0</ordinal>
                      <description>Extern gesteuert</description>
                    </enumEntry>
                    <enumEntry>
                      <literal>HC_AUTO</literal>
                      <ordinal>1</ordinal>
                      <description>Standby Betrieb</description>
                    </enumEntry>
                    <enumEntry>
                      <literal>HC_HEAT_COMF</literal>
                      <ordinal>2</ordinal>
                      <description>Komfort Betrieb</description>
                    </enumEntry>
                    <enumEntry>
                      <literal>HC_HEAT_ECO</literal>
                      <ordinal>3</ordinal>
                      <description>Reduzierter Betrieb</description>
                    </enumEntry>
                    <enumEntry>
                      <literal>HC_ANTIFREEZE</literal>
                      <ordinal>4</ordinal>
                      <description>Frostschutz / Aus</description>
                    </enumEntry>
                    <enumEntry>
                      <literal>HC_EMERGENCY_OP</literal>
                      <ordinal>5</ordinal>
                      <description>Notbetrieb</description>
                    </enumEntry>
                  </enum>
                </dataType>
                <unit>NONE</unit>
                <alternativeNames>
                  <sLV1Name>ctaHCOpState</sLV1Name>
                  <manufName>CTA_HK2_Status_UsrSet</manufName>
                </alternativeNames>
                <legibleDescription>
                  <textElement>Auslesen des aktuellen Status des Heizkreises</textElement>
                  <language>de</language>
                </legibleDescription>
              </dataPoint>
              <modbusDataPointConfiguration>
                <modbusDataType>
                  <int32U />
                </modbusDataType>
                <address>1103</address>
                <registerType>HoldRegister</registerType>
                <numberOfRegisters>2</numberOfRegisters>
              </modbusDataPointConfiguration>
            </dataPointListElement>
            <dataPointListElement>
              <dataPoint>
                <dataPointName>SupplyWaterTemp</dataPointName>
                <dataDirection>R</dataDirection>
                <presenceLevel>O</presenceLevel>
                <dataType>
                  <float32 />
                </dataType>
                <unit>DEGREES_CELSIUS</unit>
                <alternativeNames>
                  <sLV1Name>SupplyWaterTemp</sLV1Name>
                  <manufName>CTA_B21_Temp</manufName>
                </alternativeNames>
                <legibleDescription>
                  <textElement>Auslesen der aktuellen aktuellen-Temperatur des Vorlaufs.</textElement>
                  <language>de</language>
                </legibleDescription>
              </dataPoint>
              <modbusDataPointConfiguration>
                <modbusDataType>
                  <float32 />
                </modbusDataType>
                <address>2002</address>
                <registerType>InputRegister</registerType>
                <numberOfRegisters>2</numberOfRegisters>
              </modbusDataPointConfiguration>
            </dataPointListElement>
            <dataPointListElement>
              <dataPoint>
                <dataPointName>SupplyWaterTempStpt</dataPointName>
                <dataDirection>RW</dataDirection>
                <presenceLevel>O</presenceLevel>
                <dataType>
                  <float32 />
                </dataType>
                <unit>DEGREES_CELSIUS</unit>
                <alternativeNames>
                  <sLV1Name>SupplyWaterTempStpt</sLV1Name>
                  <manufName>CTA_Ext_Heating_Setpoint_2 (?Reserve)</manufName>
                </alternativeNames>
                <legibleDescription>
                  <textElement>Setzen der aktuellen Soll-Temperatur des Vorlaufs (Grundwert).</textElement>
                  <language>de</language>
                </legibleDescription>
              </dataPoint>
              <modbusDataPointConfiguration>
                <modbusDataType>
                  <float32 />
                </modbusDataType>
                <address>1101</address>
                <registerType>HoldRegister</registerType>
                <numberOfRegisters>2</numberOfRegisters>
              </modbusDataPointConfiguration>
            </dataPointListElement>
            <dataPointListElement>
              <dataPoint>
                <dataPointName>ctaRemoteHCTempSetptEnable</dataPointName>
                <dataDirection>RW</dataDirection>
                <presenceLevel>M</presenceLevel>
                <dataType>
                  <boolean/>
                </dataType>
                <unit>NONE</unit>
                <alternativeNames>
                	<sLV1Name>ctaRemoteHCTempSetptEnable</sLV1Name>
                	<manufName>CTA_Ext_Heating_Command_2 (?Reserve)</manufName></alternativeNames>
                <legibleDescription>
                  <textElement>true um den Datenpunkt HeatCoolCtrl.SupplyWaterTempStpt zu aktvieren</textElement>
                  <language>de</language>
                </legibleDescription>
                <programmerHints>
                  <textElement>true sets the CTA_Ext_Heating_Setpoint to active AND forces the ctaHCOpModeCmd into HC_COMFORT mode as long ctaRemoteCtrlTimeSec > 0
                  when the ctaRemoteHCTempSetptEnable becomes 0, HeatCoolCtrl will stay in comfort mode until a new ctaHCOpModeCmd is set</textElement>
                  <language>en</language>
                </programmerHints>
              </dataPoint>
              <modbusDataPointConfiguration>
                <modbusDataType>
                  <int16 />
                </modbusDataType>
                <address>1100</address>
                <registerType>HoldRegister</registerType>
                <numberOfRegisters>1</numberOfRegisters>
              </modbusDataPointConfiguration>
            </dataPointListElement>
            <dataPointListElement>
              <dataPoint>
                <dataPointName>ReturnSupplyWaterTemp</dataPointName>
                <dataDirection>R</dataDirection>
                <presenceLevel>O</presenceLevel>
                <dataType>
                  <float32 />
                </dataType>
                <unit>DEGREES_CELSIUS</unit>
                <alternativeNames>
                  <sLV1Name>ReturnSupplyWaterTemp</sLV1Name>
                  <manufName>CTA_B71_Temp</manufName>
                </alternativeNames>
                <legibleDescription>
                  <textElement>Auslesen der aktuellen aktuellen-Temperatur des Rücklaufs.</textElement>
                  <language>de</language>
                </legibleDescription>
              </dataPoint>
              <modbusDataPointConfiguration>
                <modbusDataType>
                  <float32 />
                </modbusDataType>
                <address>2004</address>
                <registerType>InputRegister</registerType>
                <numberOfRegisters>2</numberOfRegisters>
              </modbusDataPointConfiguration>
            </dataPointListElement>
          </dataPointList>
        </functionalProfileListElement>
        
        
        <functionalProfileListElement>
          <functionalProfile>
            <functionalProfileName>DomHotWaterCtrl</functionalProfileName>
            <functionalProfileIdentification>
              <specificationOwnerIdentification>0</specificationOwnerIdentification>
              <functionalProfileCategory>HeatPumpControl</functionalProfileCategory>
              <functionalProfileType>DomHotWaterCtrl</functionalProfileType>
              <levelOfOperation>4m</levelOfOperation>
              <versionNumber>
                <primaryVersionNumber>0</primaryVersionNumber>
                <secondaryVersionNumber>1</secondaryVersionNumber>
                <subReleaseVersionNumber>2</subReleaseVersionNumber>
              </versionNumber>
            </functionalProfileIdentification>
            <legibleDescription>
              <textElement>
                Dieses Profil definiert die erweiterten Datenpunkte zum Grundprofil "HeatPumpBase",
                welche zur Steuerung eines Brauchwarmwasserkreises zur Verfügung gestellt werden.
                Das Brauchwarmwasser-Profil muss immer in Kombination mit dem Grundprofil der
                Wärmepumpe bewirtschaftet werden.
              </textElement>
              <language>de</language>
            </legibleDescription>
          </functionalProfile>
          <dataPointList>
            <dataPointListElement>
              <dataPoint>
                <dataPointName>ctaDomHotWOpModeCmd</dataPointName>
                <dataDirection>RWP</dataDirection>
                <presenceLevel>M</presenceLevel>
                <dataType>
                  <enum>
                    <enumEntry>
                      <literal>DHW_ON</literal>
                      <ordinal>1</ordinal>
                    </enumEntry>
                    <enumEntry>
                      <literal>DHW_OFF</literal>
                      <ordinal>2</ordinal>
                    </enumEntry>
                    <enumEntry>
                      <literal>DHW_PUSH</literal>
                      <ordinal>3</ordinal>
                    </enumEntry>
                    <enumEntry>
                      <literal>DHW_EMERGENCY_OP</literal>
                      <ordinal>5</ordinal>
                    </enumEntry>
                  </enum>
                </dataType>
                <unit>NONE</unit>
                <alternativeNames>
                  <sLV1Name>ctaDomHotWOpModeCmd</sLV1Name>
                  <manufName>CTA_DW_Status_UsrSet</manufName>
                </alternativeNames>
                <legibleDescription>
                  <textElement>
                    Die Betriebsarten dieses Gerätes sind herstellerspezifisch:
                    Ein- und ausschalten, einmaliger Leistungsstoss und  Notbetrieb TWW  
                  </textElement>
                  <language>de</language>
                </legibleDescription>
              </dataPoint>
              <modbusDataPointConfiguration>
                <modbusDataType>
                  <int16U />
                </modbusDataType>
                <address>1013</address>
                <registerType>HoldRegister</registerType>
                <numberOfRegisters>1</numberOfRegisters>
              </modbusDataPointConfiguration>
            </dataPointListElement>
            <dataPointListElement>
              <dataPoint>
                <dataPointName>ctaDomHotWOpState</dataPointName>
                <dataDirection>R</dataDirection>
                <presenceLevel>M</presenceLevel>
                <dataType>
                  <enum>
                    <enumEntry>
                      <literal>DHW_INACTIVE</literal>
                      <ordinal>0</ordinal>
                    </enumEntry>
                    <enumEntry>
                      <literal>DHW_ON</literal>
                      <ordinal>1</ordinal>
                    </enumEntry>
                    <enumEntry>
                      <literal>DHW_OFF</literal>
                      <ordinal>2</ordinal>
                    </enumEntry>
                    <enumEntry>
                      <literal>DHW_PUSH</literal>
                      <ordinal>3</ordinal>
                    </enumEntry>
                    <enumEntry>
                      <literal>DHW_HOLIDAY_IS_SELECTED</literal>
                      <ordinal>4</ordinal>
                    </enumEntry>
                    <enumEntry>
                      <literal>DHW_EMERGENCY_OP</literal>
                      <ordinal>5</ordinal>
                    </enumEntry>
                    <enumEntry>
                      <literal>DHW_AUTOMATED_LEGIO_RUN</literal>
                      <ordinal>6</ordinal>
                    </enumEntry>
                  </enum>
                </dataType>
                <unit>NONE</unit>
                <alternativeNames>
                  <sLV1Name>ctaDomHotWOpState</sLV1Name>
                  <manufName>CTA_DW_Status_UsrSet</manufName>
                </alternativeNames>
                <legibleDescription>
                  <textElement>
                    Die Betriebsarten dieses Gerätes sind herstellerspezifisch:
                    Ein- und ausschalten, einmaliger Leistungsstoss, Ferienschaltung (kann nur vor Ort gesetzt werden), Notbetrieb TWW, und (nicht setzbare) automatische Legionellenschaltung  
                  </textElement>
                  <language>de</language>
                </legibleDescription>
              </dataPoint>
              <modbusDataPointConfiguration>
                <modbusDataType>
                  <int16U />
                </modbusDataType>
                <address>1013</address>
                <registerType>HoldRegister</registerType>
                <numberOfRegisters>1</numberOfRegisters>
              </modbusDataPointConfiguration>
            </dataPointListElement>
            <dataPointListElement>
              <dataPoint>
                <dataPointName>DomHotWTempStpt</dataPointName>
                <dataDirection>RWP</dataDirection>
                <presenceLevel>M</presenceLevel>
                <dataType>
                  <float32 />
                </dataType>
                <unit>DEGREES_CELSIUS</unit>
                <alternativeNames>
                  <sLV1Name>DomHotWTempStpt</sLV1Name>
                  <manufName>CTA_DW_SetpointComfort</manufName>
                </alternativeNames>
                <legibleDescription>
                  <textElement>
                    Zieltemperatur fuer den Brauchwarmwasserspeicher.
                  </textElement>
                  <language>de</language>
                </legibleDescription>
              </dataPoint>
              <modbusDataPointConfiguration>
                <modbusDataType>
                  <float32 />
                </modbusDataType>
                <address>1015</address>
                <registerType>HoldRegister</registerType>
                <numberOfRegisters>2</numberOfRegisters>
              </modbusDataPointConfiguration>
            </dataPointListElement>
            <dataPointListElement>
              <dataPoint>
                <dataPointName>ActDomHotWTemp</dataPointName>
                <dataDirection>R</dataDirection>
                <presenceLevel>M</presenceLevel>
                <dataType>
                  <float32 />
                </dataType>
                <unit>DEGREES_CELSIUS</unit>
                <alternativeNames>
                  <sLV1Name>ActDomHotWTemp</sLV1Name>
                  <manufName>CTA_B3_Temp</manufName>
                </alternativeNames>
                <legibleDescription>
                  <textElement>Aktuelle Ist-Temperatur des Brauchwarmwasserspeichers</textElement>
                  <language>de</language>
                </legibleDescription>
              </dataPoint>
              <modbusDataPointConfiguration>
                <modbusDataType>
                  <float32 />
                </modbusDataType>
                <address>2010</address>
                <registerType>InputRegister</registerType>
                <numberOfRegisters>2</numberOfRegisters>
              </modbusDataPointConfiguration>
            </dataPointListElement>
          </dataPointList>
        </functionalProfileListElement>
        <functionalProfileListElement>
          <functionalProfile>
            <functionalProfileName>BufferStorageCtrl</functionalProfileName>
            <functionalProfileIdentification>
              <specificationOwnerIdentification>0</specificationOwnerIdentification>
              <functionalProfileCategory>HeatPumpControl</functionalProfileCategory>
              <functionalProfileType>BufferStorageCtrl</functionalProfileType>
              <levelOfOperation>4m</levelOfOperation>
              <versionNumber>
                <primaryVersionNumber>0</primaryVersionNumber>
                <secondaryVersionNumber>1</secondaryVersionNumber>
                <subReleaseVersionNumber>2</subReleaseVersionNumber>
              </versionNumber>
            </functionalProfileIdentification>
            <legibleDescription>
              <textElement>Bufferspeichersteuerung mittels Temperaturoffset.</textElement>
              <language>de</language>
            </legibleDescription>
          </functionalProfile>
          <dataPointList>
            <dataPointListElement>
              <dataPoint>
                <dataPointName>HeatBufferTempStptOffset</dataPointName>
                <dataDirection>RWP</dataDirection>
                <presenceLevel>M</presenceLevel>
                <dataType>
                  <float32 />
                </dataType>
                <unit>DEGREES_CELSIUS</unit>
                <alternativeNames>
                  <sLV1Name>HeatBufferTempStptOffset</sLV1Name>
                  <manufName>CTA_CFG_Buffer_Overcharge_dT</manufName>
                </alternativeNames>
                <legibleDescription>
                  <textElement>Relative Anhebung/Absenkung der Solltemperatur (+/-) für den
                    Heiz-Pufferspeicher.</textElement>
                  <language>de</language>
                </legibleDescription>
              </dataPoint>
              <genericAttributes>
                <maxVal>50.0</maxVal>
                <minVal>-50.0</minVal>
              </genericAttributes>
              <modbusDataPointConfiguration>
                <modbusDataType>
                  <float32 />
                </modbusDataType>
                <address>1032</address>
                <registerType>HoldRegister</registerType>
                <numberOfRegisters>2</numberOfRegisters>
              </modbusDataPointConfiguration>
            </dataPointListElement>
            <dataPointListElement>
              <dataPoint>
                <dataPointName>ActHeatBufferTempUpper</dataPointName>
                <dataDirection>R</dataDirection>
                <presenceLevel>M</presenceLevel>
                <dataType>
                  <float32 />
                </dataType>
                <unit>DEGREES_CELSIUS</unit>
                <alternativeNames>
                	<sLV1Name>ActHeatBufferTempUpper</sLV1Name>
                	<manufName>CTA_B4_Temp</manufName></alternativeNames>
                <legibleDescription>
                  <textElement>Aktuelle Ist-Temperatur des
                    Heiz-Pufferspeichers oben</textElement>
                  <language>de</language>
                </legibleDescription>
              </dataPoint>
              <modbusDataPointConfiguration>
                <modbusDataType>
                  <float32 />
                </modbusDataType>
                <address>2014</address>
                <registerType>HoldRegister</registerType>
                <numberOfRegisters>2</numberOfRegisters>
              </modbusDataPointConfiguration>
            </dataPointListElement>
            <dataPointListElement>
              <dataPoint>
                <dataPointName>ActHeatBufferTempLower</dataPointName>
                <dataDirection>R</dataDirection>
                <presenceLevel>O</presenceLevel>
                <dataType>
                  <float32 />
                </dataType>
                <unit>DEGREES_CELSIUS</unit>
                <alternativeNames>
                	<sLV1Name>ActHeatBufferTempLower</sLV1Name>
                	<manufName>CTA_B41_Temp</manufName></alternativeNames>
                <legibleDescription>
                  <textElement>Aktuelle Ist-Temperatur des Heiz-Pufferspeichers unten</textElement>
                  <language>de</language>
                </legibleDescription>
              </dataPoint>
              <modbusDataPointConfiguration>
                <modbusDataType>
                  <float32 />
                </modbusDataType>
                <address>2016</address>
                <registerType>HoldRegister</registerType>
                <numberOfRegisters>2</numberOfRegisters>
              </modbusDataPointConfiguration>
            </dataPointListElement>
          </dataPointList>
        </functionalProfileListElement>
             
        <functionalProfileListElement>
          <functionalProfile>
            <functionalProfileName>SG-ReadyStates_bwp</functionalProfileName>
            <functionalProfileIdentification>
              <specificationOwnerIdentification>0</specificationOwnerIdentification>
              <functionalProfileCategory>HeatPumpControl</functionalProfileCategory>
              <functionalProfileType>SG-ReadyStates_bwp</functionalProfileType>
              <levelOfOperation>2m</levelOfOperation>
              <versionNumber>
                <primaryVersionNumber>1</primaryVersionNumber>
                <secondaryVersionNumber>0</secondaryVersionNumber>
                <subReleaseVersionNumber>0</subReleaseVersionNumber>
              </versionNumber>
            </functionalProfileIdentification>
            <legibleDescription>
              <textElement>                
            <![CDATA[	
              <h4>Wärmepumpen mit 4 Betriebszuständen</h4>
              <p>Stufe 2m Funktionsprofil mit Rücklesefunktion für Wärmepumpen mit 4 Betriebszuständen (SG Ready Wärmepumpen)</p>
              <p>Dieses Funktionsprofil bildet die beiden SG-Ready Klemmenkontakte auf einen maschinenlesbaren Zustand ab</p>
              <ul>
                <li><strong>HP_LOCKED</strong>: EVU-Sperre und umfasst im Normalfall maximal 2 Stunden „harte“ Sperrzeit </li>
                <li><strong>HP_NORMAL</strong>: Wärmepumpe im Normalbetrieb</li>
                <li><strong>HP_INTENSIFIED</strong>: Einschaltempfehlung mit Anhebung</li>
                <li><strong>HP_FORCED</strong>: Definitiver Anlaufbefehl (insofern dieser im Rahmen der Regeleinstellungen möglich ist)</li>  				
              </ul>
              <p>Der Communicator (z.B. CEM) berücksichtigt die Gerätevorgaben zur Schaltfrequenz (Attribute maxLockTimeMintues und minRunTimeMinutes).</p>
              <p>„SG Ready“ ist ein Markenzeichen des Bundesverbands Wärmepumpe e. V.<br/>
                 Weiterführende Informationen unter <a href="https://www.waermepumpe.de/normen-technik/sg-ready/">https://www.waermepumpe.de/normen-technik/sg-ready/</a>).</p>
            ]]>
          </textElement>
              <language>de</language>
            </legibleDescription>
          </functionalProfile>
          <genericAttributes>
            <maxLockTimeMinutes>120</maxLockTimeMinutes>
            <minRunTimeMinutes>20</minRunTimeMinutes>
          </genericAttributes>
          <dataPointList>
            <dataPointListElement>
              <dataPoint>
                <dataPointName>SGReadyOpModeCmd</dataPointName>
                <dataDirection>RW</dataDirection>
                <presenceLevel>M</presenceLevel>
                <dataType>
                  <enum>
                    <enumEntry>
                      <literal>HP_LOCKED</literal>
                      <ordinal>1</ordinal>
                      <description>Gesperrt für maximal 2h</description>
                    </enumEntry>
                    <enumEntry>
                      <literal>HP_NORMAL</literal>
                      <ordinal>2</ordinal>
                      <description>Normalbetrieb, optimiert auf den Kunden</description>
                    </enumEntry>
                    <enumEntry>
                      <literal>HP_INTENSIFIED</literal>
                      <ordinal>3</ordinal>
                      <description>Verstärkter Betrieb</description>
                    </enumEntry>
                    <enumEntry>
                      <literal>HP_FORCED</literal>
                      <ordinal>4</ordinal>
                      <description>Definitiver Anlaufbefehl</description>
                    </enumEntry>
                  </enum>
                </dataType>
                <unit>NONE</unit>
                <alternativeNames>
                  <sLV1Name>SGReadyOpModeCmd</sLV1Name>
                  <manufName>CTA_Ext_SG</manufName>
                  <hpBwpName>Betriebsmodus</hpBwpName>
                </alternativeNames>
                <legibleDescription>
                  <textElement>this the command acccording the bwp SG-Ready definition
                    https://www.waermepumpe.de/normen-technik/sg-ready/</textElement>
                  <language>en</language>
                </legibleDescription>
                <programmerHints>
                  <textElement>
                    SG READY BETRIEBSZUSTAND 1: Die Anlage darf
                    nicht starten. Nur der Frostschutz wird
                    gewährleistet. 2: Normaler Betrieb der Anlage.
                    Automatik- / Programmbetrieb gemäß BI der
                    angeschlossenen Wärmepumpe 3: Forcierter Betrieb
                    der Anlage mit erhöhten Werten für Heiz-
                    und/oder Warmwassertemperatur 4: Sofortige
                    Ansteuerung der Maximalwerte für Heiz- und
                    Warmwassertemperatur
                  </textElement>
                  <language>de</language>
                </programmerHints>
              </dataPoint>
              <modbusDataPointConfiguration>
                <modbusDataType>
                  <int16U />
                </modbusDataType>
                <address>1054</address>
                <registerType>HoldRegister</registerType>
                <numberOfRegisters>1</numberOfRegisters>
              </modbusDataPointConfiguration>
            </dataPointListElement>
            <dataPointListElement>
              <dataPoint>
                <dataPointName>SGReadyState</dataPointName>
                <dataDirection>R</dataDirection>
                <presenceLevel>M</presenceLevel>
                <dataType>
                  <enum>
                    <enumEntry>
                      <literal>HP_LOCKED</literal>
                      <ordinal>1</ordinal>
                      <description>Gesperrt für maximal 2h</description>
                    </enumEntry>
                    <enumEntry>
                      <literal>HP_NORMAL</literal>
                      <ordinal>2</ordinal>
                      <description>Normalbetrieb, optimiert auf den Kunden</description>
                    </enumEntry>
                    <enumEntry>
                      <literal>HP_INTENSIFIED</literal>
                      <ordinal>3</ordinal>
                      <description>Verstärkter Betrieb</description>
                    </enumEntry>
                    <enumEntry>
                      <literal>HP_FORCED</literal>
                      <ordinal>4</ordinal>
                      <description>Definitiver Anlaufbefehl</description>
                    </enumEntry>
                  </enum>
                </dataType>
                <unit>NONE</unit>
                <alternativeNames>
                  <sLV1Name>SGReadyState</sLV1Name>
                  <manufName>CTA_Ext_SG</manufName>
                  <hpBwpName>Statusmeldungen</hpBwpName>
                </alternativeNames>
                <legibleDescription>
                  <textElement>Rückmeldung der aktuellen laufenden Übersteuerungsmoeglichkeit der
                    Wärmepumpe</textElement>
                  <language>de</language>
                </legibleDescription>
              </dataPoint>
              <modbusDataPointConfiguration>
                <modbusDataType>
                  <int16U />
                </modbusDataType>
                <address>1054</address>
                <registerType>HoldRegister</registerType>
                <numberOfRegisters>1</numberOfRegisters>
              </modbusDataPointConfiguration>
            </dataPointListElement>
          </dataPointList>
        </functionalProfileListElement>
        <functionalProfileListElement>
          <functionalProfile>
            <functionalProfileName>EnergyMonitor</functionalProfileName>
            <functionalProfileIdentification>
              <specificationOwnerIdentification>0</specificationOwnerIdentification>
              <functionalProfileCategory>HeatPumpControl</functionalProfileCategory>
              <functionalProfileType>EnergyMonitor</functionalProfileType>
              <levelOfOperation>m</levelOfOperation>
              <versionNumber>
                <primaryVersionNumber>0</primaryVersionNumber>
                <secondaryVersionNumber>1</secondaryVersionNumber>
                <subReleaseVersionNumber>2</subReleaseVersionNumber>
              </versionNumber>
            </functionalProfileIdentification>
            <legibleDescription>
              <textElement>Das Profil definiert den Monitoringbaustein zur Auswertung des Energieverbrauchs
                der Wärmepumpe</textElement>
              <language>de</language>
            </legibleDescription>
          </functionalProfile>
          <dataPointList>
            <dataPointListElement>
              <dataPoint>
                <dataPointName>ActiveEnergyACtot</dataPointName>
                <dataDirection>R</dataDirection>
                <presenceLevel>R</presenceLevel>
                <dataType>
                  <float32 />
                </dataType>
                <unit>KILOWATT_HOURS</unit>
                <alternativeNames>
                  <manufName>CTA_Energy_El_Tot</manufName>
                </alternativeNames>
                <legibleDescription>
                  <textElement>Summe der aufgenommenen elektrischen Energie des Verdichters inkl.
                    Hilfsaggregate total.</textElement>
                  <language>de</language>
                </legibleDescription>
              </dataPoint>
              <modbusDataPointConfiguration>
                <modbusDataType>
                  <int32U />
                </modbusDataType>
                <address>2074</address>
                <registerType>InputRegister</registerType>
                <numberOfRegisters>2</numberOfRegisters>
              </modbusDataPointConfiguration>
            </dataPointListElement>
            <dataPointListElement>
              <dataPoint>
                <dataPointName>ActiveEnergyACheat</dataPointName>
                <dataDirection>R</dataDirection>
                <presenceLevel>R</presenceLevel>
                <dataType>
                  <float32 />
                </dataType>
                <unit>KILOWATT_HOURS</unit>
                <alternativeNames>
                  <manufName>CTA_Energy_El_Heat</manufName>
                </alternativeNames>
                <legibleDescription>
                  <textElement>Summe der aufgenommenen elektrischen Energie des Verdichters für das
                    Heizen.</textElement>
                  <language>de</language>
                </legibleDescription>
              </dataPoint>
              <modbusDataPointConfiguration>
                <modbusDataType>
                  <int32U />
                </modbusDataType>
                <address>2068</address>
                <registerType>InputRegister</registerType>
                <numberOfRegisters>2</numberOfRegisters>
              </modbusDataPointConfiguration>
            </dataPointListElement>
            <dataPointListElement>
              <dataPoint>
                <dataPointName>ActiveEnergyACDomHotW</dataPointName>
                <dataDirection>R</dataDirection>
                <presenceLevel>R</presenceLevel>
                <dataType>
                  <float32 />
                </dataType>
                <unit>KILOWATT_HOURS</unit>
                <alternativeNames>
                  <manufName>CTA_Energy_El_DW</manufName>
                </alternativeNames>
                <legibleDescription>
                  <textElement>Summe der aufgenommenen elektrischen Energie des Verdichters für das
                    Kühlen (nur bei aktiver Kühlung über Verdichter).</textElement>
                  <language>de</language>
                </legibleDescription>
              </dataPoint>
              <modbusDataPointConfiguration>
                <modbusDataType>
                  <int32U />
                </modbusDataType>
                <address>2070</address>
                <registerType>InputRegister</registerType>
                <numberOfRegisters>2</numberOfRegisters>
              </modbusDataPointConfiguration>
            </dataPointListElement>
            <dataPointListElement>
              <dataPoint>
                <dataPointName>ThermalEnergyTot</dataPointName>
                <dataDirection>R</dataDirection>
                <presenceLevel>R</presenceLevel>
                <dataType>
                  <float32 />
                </dataType>
                <unit>KILOWATT_HOURS</unit>
                <alternativeNames>
                  <sLV1Name>ThermalEnergyTot</sLV1Name>
                  <manufName>CTA_Energy_Q_Tot</manufName>
                </alternativeNames>
                <legibleDescription>
                  <textElement>Summe der abgegebenen thermischen Energie total.</textElement>
                  <language>de</language>
                </legibleDescription>
              </dataPoint>
              <modbusDataPointConfiguration>
                <modbusDataType>
                  <int32U />
                </modbusDataType>
                <address>2060</address>
                <registerType>InputRegister</registerType>
                <numberOfRegisters>2</numberOfRegisters>
              </modbusDataPointConfiguration>
            </dataPointListElement>
            <dataPointListElement>
              <dataPoint>
                <dataPointName>ThermalEnergyHeat</dataPointName>
                <dataDirection>R</dataDirection>
                <presenceLevel>R</presenceLevel>
                <dataType>
                  <float32 />
                </dataType>
                <unit>KILOWATT_HOURS</unit>
                <alternativeNames>
                  <sLV1Name>ThermalEnergyHeat</sLV1Name>
                  <manufName>CTA_Energy_Q_Heat</manufName>
                </alternativeNames>
                <legibleDescription>
                  <textElement>Summe der abgegebenen thermischen Energie für das Heizen.</textElement>
                  <language>de</language>
                </legibleDescription>
              </dataPoint>
              <modbusDataPointConfiguration>
                <modbusDataType>
                  <int32U />
                </modbusDataType>
                <address>2054</address>
                <registerType>InputRegister</registerType>
                <numberOfRegisters>2</numberOfRegisters>
              </modbusDataPointConfiguration>
            </dataPointListElement>
            <dataPointListElement>
              <dataPoint>
                <dataPointName>ThermalEnergyDomHotWater</dataPointName>
                <dataDirection>R</dataDirection>
                <presenceLevel>R</presenceLevel>
                <dataType>
                  <float32 />
                </dataType>
                <unit>KILOWATT_HOURS</unit>
                <alternativeNames>
                  <sLV1Name>ThermalEnergyDomHotWater</sLV1Name>
                  <manufName>CTA_Energy_Q_DW</manufName>
                </alternativeNames>
                <legibleDescription>
                  <textElement>Summe der aufgenommenen thermischen Energie für das Kühlen (nur bei
                    aktiver Kühlung über Verdichter).</textElement>
                  <language>de</language>
                </legibleDescription>
              </dataPoint>
              <modbusDataPointConfiguration>
                <modbusDataType>
                  <int32U />
                </modbusDataType>
                <address>2056</address>
                <registerType>InputRegister</registerType>
                <numberOfRegisters>2</numberOfRegisters>
              </modbusDataPointConfiguration>
            </dataPointListElement>
            <dataPointListElement>
              <dataPoint>
                <dataPointName>ActPowerACtot</dataPointName>
                <dataDirection>R</dataDirection>
                <presenceLevel>O</presenceLevel>
                <dataType>
                  <float32 />
                </dataType>
                <unit>KILOWATT_HOURS</unit>
                  <alternativeNames>
                    <sLV1Name>ActPowerACtot</sLV1Name>
                    <manufName>State_CompPower</manufName>
                  </alternativeNames>
                <legibleDescription>
                  <textElement>Effektive elektrischen Aufnahmeleistung des Verdichters</textElement>
                  <language>de</language>
                </legibleDescription>
              </dataPoint>
              <modbusDataPointConfiguration>
                <modbusDataType>
                  <float32 />
                </modbusDataType>
                <address>2032</address>
                <registerType>InputRegister</registerType>
                <numberOfRegisters>2</numberOfRegisters>
              </modbusDataPointConfiguration>
            </dataPointListElement>
            <dataPointListElement>
              <dataPoint>
                <dataPointName>RuntimeHeating</dataPointName>
                <dataDirection>R</dataDirection>
                <presenceLevel>R</presenceLevel>
                <dataType>
                  <float32 />
                </dataType>
                <unit>HOURS</unit>
                <alternativeNames>
                  <sLV1Name>RuntimeHeating</sLV1Name>
                  <manufName>CTA_OperTime_Total_h</manufName>
                </alternativeNames>
                <legibleDescription>
                  <textElement>Summe der Laufzeit des Verdichters seit Inbetriebnahme.</textElement>
                  <language>de</language>
                </legibleDescription>
              </dataPoint>
              <modbusDataPointConfiguration>
                <modbusDataType>
                  <float32 />
                </modbusDataType>
                <address>2090</address>
                <registerType>InputRegister</registerType>
                <numberOfRegisters>2</numberOfRegisters>
              </modbusDataPointConfiguration>
            </dataPointListElement>
            <dataPointListElement>
              <dataPoint>
                <dataPointName>RuntimeCooling</dataPointName>
                <dataDirection>R</dataDirection>
                <presenceLevel>R</presenceLevel>
                <dataType>
                  <float32 />
                </dataType>
                <unit>HOURS</unit>
                <alternativeNames>
                  <sLV1Name>RuntimeCooling</sLV1Name>
                  <manufName>CTA_OperTime_Cooling_h</manufName>
                </alternativeNames>
                <legibleDescription>
                  <textElement>Summe der Laufzeit in der Kühlphase.</textElement>
                  <language>de</language>
                </legibleDescription>
              </dataPoint>
              <modbusDataPointConfiguration>
                <modbusDataType>
                  <int32U />
                </modbusDataType>
                <address>2092</address>
                <registerType>InputRegister</registerType>
                <numberOfRegisters>2</numberOfRegisters>
              </modbusDataPointConfiguration>
            </dataPointListElement>
            <dataPointListElement>
              <dataPoint>
                <dataPointName>NrOfStartupsCompressor</dataPointName>
                <dataDirection>R</dataDirection>
                <presenceLevel>R</presenceLevel>
                <dataType>
                  <int32U />
                </dataType>
                <unit>NONE</unit>
                <alternativeNames>
                  <sLV1Name>NrOfStartupsCompressor</sLV1Name>
                  <manufName>CTA_CompStartAttempts</manufName>
                </alternativeNames>
                <legibleDescription>
                  <textElement>Anzahl Starts des Verdichters seit Inbetriebnahme.</textElement>
                  <language>de</language>
                </legibleDescription>
              </dataPoint>
              <modbusDataPointConfiguration>
                <modbusDataType>
                  <int32U />
                </modbusDataType>
                <address>2094</address>
                <registerType>InputRegister</registerType>
                <numberOfRegisters>2</numberOfRegisters>
              </modbusDataPointConfiguration>
            </dataPointListElement>
          </dataPointList>
        </functionalProfileListElement>
      </functionalProfileList>
    </modbusInterface>
  </interfaceList>
</DeviceFrame>
